README.txt
setup.cfg
setup.py
cs/__init__.py
cs.autotranslate.egg-info/PKG-INFO
cs.autotranslate.egg-info/SOURCES.txt
cs.autotranslate.egg-info/dependency_links.txt
cs.autotranslate.egg-info/entry_points.txt
cs.autotranslate.egg-info/namespace_packages.txt
cs.autotranslate.egg-info/not-zip-safe
cs.autotranslate.egg-info/paster_plugins.txt
cs.autotranslate.egg-info/requires.txt
cs.autotranslate.egg-info/top_level.txt
cs/autotranslate/__init__.py
cs/autotranslate/configure.zcml
cs/autotranslate/subscriber.py
cs/autotranslate/tests.py
cs/autotranslate/translate.py
docs/HISTORY.txt
docs/INSTALL.txt
docs/LICENSE.GPL
docs/LICENSE.txt