Metadata-Version: 1.1
Name: cs.autotranslate
Version: 1.1
Summary: Auto translate items in a folder which is specially marked
Home-page: https://github.com/codesyntax/cs.autotranslate
Author: Mikel Larreategi
Author-email: mlarreategi@codesyntax.com
License: GPL
Platform: UNKNOWN
Classifier: Framework :: Plone
Classifier: Programming Language :: Python
